{
    "name": "Priestess' Staff Dance",
    "cost": "5",
    "costType": "ep",
    "requiredLevel": "0",
    "learningCost": "250",
    "skillType": "attack",
    "statType": "Allure",
    "requiredStat": "6",
    "skillTags": ["Seduction"],
    "fetishTags": [""],
    "startsStance": "",
    "requiresStance": "Any",
    "unusableIfStance": ["Any"],
    "requiresTargetStance": ["Any"],
    "unusableIfTarget": [""],
    "removesStance": "None",
    "requiresStatusEffect": "None",
    "requiresStatusPotency": "0",
    "unusableIfStatusEffect": ["None"],
    "power": "35",
    "minRange": "90",
    "maxRange": "110",
    "recoil": "0",
    "targetType": "single",
    "statusEffect": "Charm",
    "statusChance": "70",
    "statusDuration": "3",
    "statusPotency": "0",
    "statusResistedBy": "Willpower",
    "statusText": "",
    "descrip": "",
    "outcome": "[AttackerName] plants [AttackerHisOrHer] staff in the ground, sensually moving her body beside it. Placing the pole between her full breasts, [AttackerHeOrShe] lewdly grinds her crotch against it. The display is irresistably arousing, making [TargetName] flush.",
    "miss": "[AttackerName] plants [AttackerHisOrHer] staff in the ground, sensually moving her body beside it. Placing the pole between her full breasts, [AttackerHeOrShe] lewdly grinds her crotch against it. But [TargetName] manages to ignore the sexy display.",
    "statusOutcome": "[TargetName]'s cheeks flush with color! [TargetName] is charmed!",
    "statusMiss": "",
    "restraintStruggle": "",
    "restraintStruggleCharmed": "",
    "restraintEscaped": "",
    "restraintEscapedFail": ""
}
